{"id": "np/kaatthekholaa-gaaunpaalikaa", "name": "\u0915\u093e\u0920\u0947\u0916\u094b\u0932\u093e \u0917\u093e\u0909\u0901\u092a\u093e\u0932\u093f\u0915\u093e", "abbreviation": "", "other_names": "", "description": "", "classification": "", "parent_id": "", "founding_date": "", "dissolution_date": "", "image": "", "url": "http://kathekholamun.gov.np", "jurisdiction_code": "NP", "phone": "9857620694", "email": "kathekholagahunpalika123@gmail.com", "address": "\u092c\u093e\u0917\u094d\u0932\u0941\u0919", "contact": "", "tags": "local bodies, rural municipality", "source_url": ""}