{"id": "np/maadhvnaaraaynn-ngrpaalikaa", "name": "\u092e\u093e\u0927\u0935\u0928\u093e\u0930\u093e\u092f\u0923 \u0928\u0917\u0930\u092a\u093e\u0932\u093f\u0915\u093e", "abbreviation": "", "other_names": "", "description": "", "classification": "", "parent_id": "", "founding_date": "", "dissolution_date": "", "image": "", "url": "http://madhavnarayanmun.gov.np", "jurisdiction_code": "NP", "phone": "9855044025", "email": "info@madhavnarayanmun.gov.np", "address": "\u0930\u094c\u0924\u0939\u091f", "contact": "", "tags": "local bodies, municipality", "source_url": ""}