{"id": "de/amt-fur-geoinformationswesen-der-bundeswehr", "name": "Amt f\u00fcr Geoinformationswesen der Bundeswehr", "abbreviation": "", "other_names": "", "description": "", "classification": "Andere", "parent_id": "", "founding_date": "", "dissolution_date": "", "image": "", "url": "http://www.sowi.bundeswehr.de", "jurisdiction_code": "DE", "phone": "", "email": "ageobwinformationsarbeit@bundeswehr.org", "address": "Frauenberger Stra\u00dfe\u00a0250\n53879 Euskirchen, Nordrhein-Westfalen\nDeutschland\nTelefon:\u00a0\n+49 2251 953-4130\nFax:\u00a0\n+49 2251 953-5055\nageobwinformationsarbeit@bundeswehr.org", "contact": "Hauptadresse\nFrauenberger Stra\u00dfe\u00a0250\n53879 Euskirchen, Nordrhein-Westfalen\nDeutschland\nTelefon:\u00a0\n+49 2251 953-4130\nFax:\u00a0\n+49 2251 953-5055\nageobwinformationsarbeit@bundeswehr.org", "tags": "Amt f\u00fcr Geoinformationswesen der Bundeswehr, AGeoBw, Milit\u00e4rgeographie, Kartenwesen, Vermessungswesen", "source_url": ""}