{"id": "de/deutsche-investitions-und-entwicklungsgesellschaft", "name": "Deutsche Investitions- und Entwicklungsgesellschaft", "abbreviation": "", "other_names": "", "description": "Die DEG f\u00f6rdert im Rahmen der Entwicklungspolitik der Bundesregierung private Unternehmen in Partnerl\u00e4ndern (Entwicklungs- oder Transforml\u00e4ndern) sowie deren Zusammenarbeit mit deutschen und anderen europ\u00e4ischen Unternehmen. Sie ist Ansprechpartner f\u00fcr private Investitionen und andere Formen der langfristigen Unternehmenskooperation.\n\nSiehe http://www.bund.de/DE/Behoerden/D/DEG/Deutsche-Investitions-und-Entwicklungsgesellschaft.html", "classification": "Andere", "parent_id": "", "founding_date": "", "dissolution_date": "", "image": "", "url": "http://www.deginvest.de", "jurisdiction_code": "DE", "phone": "", "email": "info@deginvest.de", "address": "", "contact": "Hauptsitz\nK\u00e4mmerga\u00dfe\u00a022\n50676 K\u00f6ln, Nordrhein-Westfalen\nDeutschland\nPostanschrift:\nPostfach 10 09 61, 50449 K\u00f6ln\nTelefon:\u00a0\n+49 221 4986-0\nFax:\u00a0\n+49 221 4986-1290\ninfo@deginvest.de", "tags": "Deutsche Investitions- und Entwicklungsgesellschaft mbH, DEG, Entwicklung, Entwicklungspolitik", "source_url": ""}