{"id": "de/kulturveranstaltungen-des-bundes-in-berlin-gmbh", "name": "Kulturveranstaltungen des Bundes in Berlin GmbH", "abbreviation": "", "other_names": "", "description": "", "classification": "Andere", "parent_id": "", "founding_date": "", "dissolution_date": "", "image": "", "url": "http://www.kbberlin.de", "jurisdiction_code": "DE", "phone": "", "email": "info@kbb.eu", "address": "Sch\u00f6neberger Stra\u00dfe\u00a015\n10963 Berlin, Berlin\nDeutschland\nTelefon:\u00a0\n+49 30 26397-0\nFax:\u00a0\n+49 30 26397-397\ninfo@kbb.eu\n\n\n  \nBerliner Festspiele\nSchaper Str.\u00a024\n10719 Berlin, Berlin\nDeutschland\nTelefon:\u00a0\n+49 30 25489-0\nFax:\u00a0\n+49 30 25489-111\ninfo@berlinerfestspiele.de\n\n  \nHaus der Kulturen der Welt\nJohn-Foster-Dulles-Allee\u00a010\n10557 Berlin, Berlin\nDeutschland\nTelefon:\u00a0\n+49 30 397870\nFax:\u00a0\n+49 30 3948679\ninfo@hkw.de\n\n  \nInternationale Filmfestspiele Berlin\nPotsdamer Str.\u00a05\n10785 Berlin, Berlin\nDeutschland\nTelefon:\u00a0\n+49 30 25920-0\nFax:\u00a0\n+4930 25920-299\ninfo@berlinale.de\n\n  \nMartin-Gropius-Bau\nNiederkirchnerstra\u00dfe 7 // Ecke Stresemannstra\u00dfe 110\n10963 Berlin, Berlin\nDeutschland\nTelefon:\u00a0\n+49 30 25486-112\nFax:\u00a0\n+49 30 25486-107\npost@gropiusbau.berlinerfestspiele.de", "contact": "Hauptadresse\nSch\u00f6neberger Stra\u00dfe\u00a015\n10963 Berlin, Berlin\nDeutschland\nTelefon:\u00a0\n+49 30 26397-0\nFax:\u00a0\n+49 30 26397-397\ninfo@kbb.eu", "tags": "Kulturveranstaltungen des Bundes in Berlin GmbH, KBB, Kultur, Kulturaustausch", "source_url": ""}