{"id": "it/a-a-t-o-me-3-s-i-i-in-liquidazione", "name": "A.A.T.O. Me 3 S.I.I. in Liquidazione", "abbreviation": "ATOACQUEME", "other_names": "", "description": "", "classification": "Enti di Regolazione dei Servizi Idrici e o dei Rifiuti", "parent_id": "", "founding_date": "", "dissolution_date": "", "image": "", "url": "https://atoacquemessina@pec.it", "jurisdiction_code": "IT", "phone": "", "email": "atoacquemessina@pec.it", "address": "Via XXIV Maggio Citta' Metropolitana Palazzo Degli Uffici - 98122 Messina (ME) Italy", "contact": "", "tags": "", "source_url": "http://www.indicepa.gov.it/ricerca/n-dettaglioamministrazione.php?cod_amm=aatom"}