{"id": "it/ag-naz-attrazione-investimenti-sviluppo-impresa-spa", "name": "Ag.Naz.Attrazione Investimenti Sviluppo Impresa Spa", "abbreviation": "INVITALIA", "other_names": "", "description": "", "classification": "Societa' in Conto Economico Consolidato", "parent_id": "", "founding_date": "", "dissolution_date": "", "image": "", "url": "https://www.invitalia.it/", "jurisdiction_code": "IT", "phone": "", "email": "invitalia@pec.invitalia.it", "address": "Via Calabria  46 - 187 Roma (RM) Italy", "contact": "", "tags": "", "source_url": "http://www.indicepa.gov.it/ricerca/n-dettaglioamministrazione.php?cod_amm=anais"}