{"id": "it/aspm-servizi-ambientali-s-r-l", "name": "Aspm Servizi Ambientali S.R.L.", "abbreviation": "", "other_names": "", "description": "", "classification": "Gestori di Pubblici Servizi", "parent_id": "", "founding_date": "", "dissolution_date": "", "image": "", "url": "https://www.aspmambientale.it", "jurisdiction_code": "IT", "phone": "", "email": "asa.protocollo@legalmail.it", "address": "Via Cairoli  17 - 26015 Soresina (CR) Italy", "contact": "", "tags": "", "source_url": "http://www.indicepa.gov.it/ricerca/n-dettaglioamministrazione.php?cod_amm=asasr"}