{"id": "it/ater-provincia-aquila", "name": "ATER Provincia Aquila", "abbreviation": "", "other_names": "", "description": "", "classification": "Stazioni Appaltanti", "parent_id": "", "founding_date": "", "dissolution_date": "", "image": "", "url": "https://ateraq.it/", "jurisdiction_code": "IT", "phone": "", "email": "posta.certificata@ateraq.legalmail.it", "address": "Via Antica Arischia 46e - 67100 L'Aquila (AQ) Italy", "contact": "", "tags": "", "source_url": "http://www.indicepa.gov.it/ricerca/n-dettaglioamministrazione.php?cod_amm=6PAVRHY5"}