{"id": "it/autorita-di-regolazione-per-energia-reti-e-ambiente", "name": "Autorita' di Regolazione per Energia Reti e Ambiente", "abbreviation": "ARERA", "other_names": "", "description": "", "classification": "Autorita' Amministrative Indipendenti", "parent_id": "", "founding_date": "", "dissolution_date": "", "image": "", "url": "https://www.arera.it", "jurisdiction_code": "IT", "phone": "", "email": "protocollo@pec.arera.it", "address": "Corso di Porta Vittoria n. 27 - 20121 Milano (MI) Italy", "contact": "", "tags": "", "source_url": "http://www.indicepa.gov.it/ricerca/n-dettaglioamministrazione.php?cod_amm=AEEG"}