{"id": "it/azienda-regionale-per-il-diritto-allo-studio-universitario", "name": "Azienda Regionale per il Diritto allo Studio Universitario", "abbreviation": "DSU TOSCANA", "other_names": "", "description": "", "classification": "Agenzie, Enti e Consorzi Pubblici per il Diritto allo Studio Universitario", "parent_id": "", "founding_date": "", "dissolution_date": "", "image": "", "url": "https://www.dsu.toscana.it", "jurisdiction_code": "IT", "phone": "", "email": "dsutoscana@postacert.toscana.it", "address": "Viale Antonio Gramsci  36 - 50132 Firenze (FI) Italy", "contact": "", "tags": "", "source_url": "http://www.indicepa.gov.it/ricerca/n-dettaglioamministrazione.php?cod_amm=ardsu_to"}