{"id": "it/azienda-regionale-per-l-edilizia-residenziale-della-valle-d-aosta", "name": "Azienda Regionale per L'Edilizia Residenziale della Valle D'Aosta", "abbreviation": "ARER VDA", "other_names": "", "description": "", "classification": "Aziende e Consorzi Pubblici Territoriali per l'Edilizia Residenziale", "parent_id": "", "founding_date": "", "dissolution_date": "", "image": "", "url": "https://www.arervda.it", "jurisdiction_code": "IT", "phone": "", "email": "arervda@pec.unonet.it", "address": "Via Cesare Battisti  13 - 11100 Aosta (AO) Italy", "contact": "", "tags": "", "source_url": "http://www.indicepa.gov.it/ricerca/n-dettaglioamministrazione.php?cod_amm=arl_007"}