{"id": "it/fondazionearena-di-verona", "name": "FONDAZIONEARENA DI VERONA", "abbreviation": "FAV", "other_names": "", "description": "", "classification": "Stazioni Appaltanti", "parent_id": "", "founding_date": "", "dissolution_date": "", "image": "", "url": "https://www.arena.it/it/arena-di-verona", "jurisdiction_code": "IT", "phone": "", "email": "arenadiverona@legalmail.it", "address": "Via roma 7/d - 37121 Verona (VR) Italy", "contact": "", "tags": "", "source_url": "http://www.indicepa.gov.it/ricerca/n-dettaglioamministrazione.php?cod_amm=3I9VYT5F"}