{"id": "it/ram-rete-autostrade-mediterranee-per-la-logistica-le-infrastrutture-ed-i-trasporti-s-p-a", "name": "RAM Rete Autostrade Mediterranee per la Logistica, le Infrastrutture ed i Trasporti S.p.a.", "abbreviation": "RAM Logistica Infrastruttura e Trasporti Spa", "other_names": "", "description": "", "classification": "Societa' in Conto Economico Consolidato", "parent_id": "", "founding_date": "", "dissolution_date": "", "image": "", "url": "https://www.ramspa.it", "jurisdiction_code": "IT", "phone": "", "email": "ramspa@pec.it", "address": "Via Nomentana 2 - 161 Roma (RM) Italy", "contact": "", "tags": "", "source_url": "http://www.indicepa.gov.it/ricerca/n-dettaglioamministrazione.php?cod_amm=1VO9PWVQ"}