{"id": "gb/cambridge-university-technical-services", "name": "Cambridge University Technical Services Limited", "abbreviation": "Cambridge University Technical Services", "other_names": "", "description": "", "classification": "", "parent_id": "", "founding_date": "", "dissolution_date": "", "image": "", "url": "http://www.enterprise.cam.ac.uk", "jurisdiction_code": "GB", "phone": "", "email": "", "address": "", "contact": "", "tags": "limited university_owned_company company", "source_url": ""}