{"id": "br/agencia-nacional-de-telecomunicacoes", "name": "Ag\u00eancia Nacional de Telecomunica\u00e7\u00f5es", "abbreviation": "ANATEL", "other_names": "", "description": "\u00c0 Ag\u00eancia Nacional de Telecomunica\u00e7\u00f5es compete adotar as medidas necess\u00e1rias para o atendimento do interesse p\u00fablico  e para o desenvolvimento das telecomunica\u00e7\u00f5es brasileiras, atuando com independ\u00eancia,  imparcialidade, legalidade, impessoalidade e publicidade, e especialmente:\n\u00a0\u00a0\u00a0\u00a0\u00a0I - implementar, em sua esfera de atribui\u00e7\u00f5es, a pol\u00edtica nacional de telecomunica\u00e7\u00f5es\n\u00a0\u00a0\u00a0\u00a0\u00a0II - representar o Brasil nos organismos internacionais de telecomunica\u00e7\u00f5es, sob a coordena\u00e7\u00e3o  do Poder Executivo\n\u00a0\u00a0\u00a0\u00a0\u00a0III - elaborar e propor ao Presidente da Rep\u00fablica, por interm\u00e9dio do Ministro de Estado das  Comunica\u00e7\u00f5es, a ado\u00e7\u00e3o das medidas a que se referem os incisos I a IV do artigo anterior,  submetendo previamente a consulta p\u00fablica as relativas aos incisos I a III\n\u00a0\u00a0\u00a0\u00a0\u00a0IV - expedir normas quanto \u00e0 outorga, presta\u00e7\u00e3o e frui\u00e7\u00e3o dos servi\u00e7os de telecomunica\u00e7\u00f5es no  regime p\u00fablico\n\u00a0\u00a0\u00a0\u00a0\u00a0V - editar atos de outorga e extin\u00e7\u00e3o de direito de explora\u00e7\u00e3o do servi\u00e7o no regime p\u00fablico\n\u00a0\u00a0\u00a0\u00a0\u00a0VI - celebrar e gerenciar contratos de concess\u00e3o e fiscalizar a presta\u00e7\u00e3o do servi\u00e7o no regime  p\u00fablico, aplicando san\u00e7\u00f5es e realizando interven\u00e7\u00f5es\n\u00a0\u00a0\u00a0\u00a0\u00a0VII - controlar, acompanhar e proceder \u00e0 revis\u00e3o de tarifas dos servi\u00e7os prestados no regime  p\u00fablico, podendo fix\u00e1-las nas condi\u00e7\u00f5es previstas nesta Lei, bem como homologar reajustes\n\u00a0\u00a0\u00a0\u00a0\u00a0VIII - administrar o espectro de radiofreq\u00fc\u00eancias e o uso de \u00f3rbitas, expedindo as respectivas  normas\n\u00a0\u00a0\u00a0\u00a0\u00a0IX - editar atos de outorga e extin\u00e7\u00e3o do direito de uso de radiofreq\u00fc\u00eancia e de \u00f3rbita,  fiscalizando e aplicando san\u00e7\u00f5es\n\u00a0\u00a0\u00a0\u00a0\u00a0X - expedir normas sobre presta\u00e7\u00e3o de servi\u00e7os de telecomunica\u00e7\u00f5es no regime privado\n\u00a0\u00a0\u00a0\u00a0\u00a0XI - expedir e extinguir autoriza\u00e7\u00e3o para presta\u00e7\u00e3o de servi\u00e7o no regime privado, fiscalizando  e aplicando san\u00e7\u00f5es\n\u00a0\u00a0\u00a0\u00a0\u00a0XII - expedir normas e padr\u00f5es a serem cumpridos pelas prestadoras de servi\u00e7os de  telecomunica\u00e7\u00f5es quanto aos equipamentos que utilizarem\n\u00a0\u00a0\u00a0\u00a0\u00a0XIII - expedir ou reconhecer a certifica\u00e7\u00e3o de produtos, observados os padr\u00f5es e normas por  ela estabelecidos\n\u00a0\u00a0\u00a0\u00a0\u00a0XIV - expedir normas e padr\u00f5es que assegurem a compatibilidade, a opera\u00e7\u00e3o integrada e a  interconex\u00e3o entre as redes, abrangendo inclusive os equipamentos terminais\n\u00a0\u00a0\u00a0\u00a0\u00a0XV - realizar busca e apreens\u00e3o de bens no \u00e2mbito de sua compet\u00eancia\n\u00a0\u00a0\u00a0\u00a0\u00a0XVI - deliberar na esfera administrativa quanto \u00e0 interpreta\u00e7\u00e3o da legisla\u00e7\u00e3o de  telecomunica\u00e7\u00f5es e sobre os casos omissos\n\u00a0\u00a0\u00a0\u00a0\u00a0XVII - compor administrativamente conflitos de interesses entre prestadoras de servi\u00e7o de  telecomunica\u00e7\u00f5es\n\u00a0\u00a0\u00a0\u00a0\u00a0XVIII - reprimir infra\u00e7\u00f5es dos direitos dos usu\u00e1rios\n\u00a0\u00a0\u00a0\u00a0\u00a0XIX - exercer, relativamente \u00e0s telecomunica\u00e7\u00f5es, as compet\u00eancias legais em mat\u00e9ria de  controle, preven\u00e7\u00e3o e repress\u00e3o das infra\u00e7\u00f5es da ordem econ\u00f4mica, ressalvadas as pertencentes ao  Conselho Administrativo de Defesa Econ\u00f4mica - CADE\n\u00a0\u00a0\u00a0\u00a0\u00a0XX - propor ao Presidente da Rep\u00fablica, por interm\u00e9dio do Minist\u00e9rio das Comunica\u00e7\u00f5es, a  declara\u00e7\u00e3o de utilidade p\u00fablica, para fins de desapropria\u00e7\u00e3o ou institui\u00e7\u00e3o de servid\u00e3o  administrativa, dos bens necess\u00e1rios \u00e0 implanta\u00e7\u00e3o ou manuten\u00e7\u00e3o de servi\u00e7o no regime p\u00fablico\n\u00a0\u00a0\u00a0\u00a0\u00a0XXI - arrecadar e aplicar suas receitas\n\u00a0\u00a0\u00a0\u00a0\u00a0XXII - resolver quanto \u00e0 celebra\u00e7\u00e3o, altera\u00e7\u00e3o ou extin\u00e7\u00e3o de seus contratos, bem como quanto  \u00e0 nomea\u00e7\u00e3o, exonera\u00e7\u00e3o e demiss\u00e3o de servidores, realizando os procedimentos necess\u00e1rios, na  forma em que dispuser o regulamento\n\u00a0\u00a0\u00a0\u00a0\u00a0XXIII - contratar pessoal por prazo determinado, de acordo com o disposto na Lei n\u00ba 8.745, de  9 de dezembro de 1993\n\u00a0\u00a0\u00a0\u00a0\u00a0XXIV - adquirir, administrar e alienar seus bens\n\u00a0\u00a0\u00a0\u00a0\u00a0XXV - decidir em \u00faltimo grau sobre as mat\u00e9rias de sua al\u00e7ada, sempre admitido recurso ao  Conselho Diretor\n\u00a0\u00a0\u00a0\u00a0\u00a0XXVI - formular ao Minist\u00e9rio das Comunica\u00e7\u00f5es proposta de or\u00e7amento\n\u00a0\u00a0\u00a0\u00a0\u00a0XXVII - aprovar o seu regimento interno\n\u00a0\u00a0\u00a0\u00a0\u00a0XXVIII - elaborar relat\u00f3rio anual de suas atividades, nele destacando o cumprimento da  pol\u00edtica do setor definida nos termos do artigo anterior\n\u00a0\u00a0\u00a0\u00a0\u00a0XXIX - enviar o relat\u00f3rio anual de suas atividades ao Minist\u00e9rio das Comunica\u00e7\u00f5es e, por  interm\u00e9dio da Presid\u00eancia da Rep\u00fablica, ao Congresso Nacional\n\u00a0\u00a0\u00a0\u00a0\u00a0XXX - rever, periodicamente, os planos enumerados nos incisos II e III do artigo anterior,  submetendo-os, por interm\u00e9dio do Ministro de Estado das Comunica\u00e7\u00f5es, ao Presidente da  Rep\u00fablica, para aprova\u00e7\u00e3o\n\u00a0\u00a0\u00a0\u00a0\u00a0XXXI - promover intera\u00e7\u00e3o com administra\u00e7\u00f5es de telecomunica\u00e7\u00f5es dos pa\u00edses do Mercado  Comum do Sul - MERCOSUL, com vistas \u00e0 consecu\u00e7\u00e3o de objetivos de interesse comum\n\n\n\n\n", "classification": "Vinculado (Autarquia)", "parent_id": "br/ministerio-das-comunicacoes", "founding_date": "", "dissolution_date": "", "image": "https://dados.gov.br/wp/wp-content/uploads/2018/11/logo-anatel.gif", "url": "https://www.anatel.gov.br", "jurisdiction_code": "BR", "phone": "+55 61 231220032", "email": "presidencia@anatel.gov.br", "address": "SAUS qd 06 bloco H, 6, 2\u00ba andar\nasa sul\n70070940 Bras\u00edlia, DF\nBrazil", "contact": "", "tags": "autarquia-especial-agencia-reguladora", "source_url": "http://estruturaorganizacional.dados.gov.br/id/unidade-organizacional/25064"}