{"id": "br/companhia-brasileira-de-trens-urbanos", "name": "Companhia Brasileira de Trens Urbanos ", "abbreviation": "CBTU", "other_names": "", "description": "\u00a0\u00a0\u00a0\u00a0\u00a0I - A execu\u00e7\u00e3o dos planos e programas aprovados pelo Minist\u00e9rio dos Transportes em conson\u00e2cia com o Plano Nacional de Via\u00e7\u00e3o e destinados a reger os servil\u00e7os de transporte ferrovi\u00e1rio urbano constantes do Sistema Nacional de Transportes Urbanos\n\u00a0\u00a0\u00a0\u00a0\u00a0II - O planejamento, o estudo, os projetos, a constru\u00e7\u00e3o e a implanta\u00e7\u00e3o de servi\u00e7os de transporte de pessoas, por trem de superf\u00e9cie, nas regi\u00f5es metropolitanas, cidades e aglomerados urbanos que justifiquem a exist\u00eancia desses servi\u00e7os, em estreita conson\u00e2ncia com a pol\u00edtica de transporte e desenvolvimento urbano\n\u00a0\u00a0\u00a0\u00a0\u00a0III - A opera\u00e7\u00e3o e a explora\u00e7\u00e3o comercial dos servi\u00e7os de transporte ferrovi\u00e1rio urbano e suburbano\n\u00a0\u00a0\u00a0\u00a0\u00a0IV - O gerenciamento das participa\u00e7\u00f5es societ\u00e1rias da Uni\u00e3o, Rede Ferrovi\u00e1ria Federal S/A - RFFSA  em empresas de transporte ferrovi\u00e1rio metropolitano e urbano de pessoas\n\u00a0\u00a0\u00a0\u00a0\u00a0V - A execu\u00e7\u00e3o de atividades conexas que lhe permitam melhor atender seu objeto social\n", "classification": "Vinculado (Empresa P\u00fablica)", "parent_id": "br/ministerio-das-cidades", "founding_date": "", "dissolution_date": "", "image": "", "url": "https://www.cbtu.gov.br", "jurisdiction_code": "BR", "phone": "+55 21 37333399", "email": "faleconosco@cbtu.gov.br", "address": "SBN Quadra 1, 0, Edif\u00edcio Confedera\u00e7\u00e3o Nacional do Com\u00e9rcio - CNC, 9\u00ba ao 13\u00ba andar\nAsa Norte\n70041902 Bras\u00edlia, DF\nBrazil", "contact": "", "tags": "", "source_url": "http://estruturaorganizacional.dados.gov.br/id/unidade-organizacional/372"}