{"id": "se/burlovs-kommun", "name": "Burl\u00f6vs kommun", "abbreviation": "", "other_names": "", "description": "F\u00f6rortskommuner till storst\u00e4derna", "classification": "2.0", "parent_id": "", "founding_date": "", "dissolution_date": "", "image": "", "url": "http://www.burlov.se", "jurisdiction_code": "SE", "phone": "040-439000", "email": "burlovs.kommun@burlov.se", "address": "Box 53", "contact": "", "tags": "", "source_url": "http://skl.se/tjanster/kommunerlandsting/adressuppgifterkommuner.1246.html"}